MANIFEST.in
README.rst
requirements.txt
setup.py
baf/__init__.py
baf/info.txt
baf/manage.py
baf/version.py
baf.egg-info/PKG-INFO
baf.egg-info/SOURCES.txt
baf.egg-info/dependency_links.txt
baf.egg-info/entry_points.txt
baf.egg-info/not-zip-safe
baf.egg-info/requires.txt
baf.egg-info/top_level.txt