Metadata-Version: 1.0
Name: baf
Version: 1.0
Summary: example packaging layout
Home-page: https://github.com/kvbik/python-baf
Author: Jakub Vysoky
Author-email: jakub.vysoky@gmail.com
License: BSD
Platform: UNKNOWN
